Workbook
Name Slicer_Year: #N/A

Sheet Revenue Assumptions
A1: Month | B1: Scenario | C1: Projected_Customers | D1: Avg_Basket_EUR | E1: Revenue_EUR | F1: Operating_Cost_EUR | G1: Net_Profit_EUR | J1: Days per week | K1: 7
A2: 46388 | B2: Base | C2: 5000 | D2: 15 | E2: 75000 | F2: 51000 | G2: 24000 | J2: Weeks per month | K2: 4
A3: 46419 | B3: Base | C3: 5000 | D3: 15 | E3: 75000 | F3: 51000 | G3: 24000 | J3: Number of months | K3: 12
A4: 46447 | B4: Base | C4: 5000 | D4: 15 | E4: 75000 | F4: 51000 | G4: 24000 | J4: Years | K4: 2
A5: 46478 | B5: Base | C5: 5000 | D5: 15 | E5: 75000 | F5: 51000 | G5: 24000
A6: 46508 | B6: Base | C6: 5000 | D6: 15 | E6: 75000 | F6: 51000 | G6: 24000
A7: 46539 | B7: Base | C7: 5000 | D7: 15 | E7: 75000 | F7: 51000 | G7: 24000
A8: 46569 | B8: Base | C8: 5000 | D8: 15 | E8: 75000 | F8: 51000 | G8: 24000
A9: 46600 | B9: Base | C9: 5000 | D9: 15 | E9: 75000 | F9: 51000 | G9: 24000
A10: 46631 | B10: Base | C10: 5000 | D10: 15 | E10: 75000 | F10: 51000 | G10: 24000
A11: 46661 | B11: Base | C11: 5000 | D11: 15 | E11: 75000 | F11: 51000 | G11: 24000
A12: 46692 | B12: Base | C12: 5000 | D12: 15 | E12: 75000 | F12: 51000 | G12: 24000
A13: 46722 | B13: Base | C13: 5000 | D13: 15 | E13: 75000 | F13: 51000 | G13: 24000
A14: 46023 | B14: Base | C14: 5000 | D14: 15 | E14: 75000 | F14: 51000 | G14: 24000
A15: 46054 | B15: Base | C15: 5000 | D15: 15 | E15: 75000 | F15: 51000 | G15: 24000
A16: 46082 | B16: Base | C16: 5000 | D16: 15 | E16: 75000 | F16: 51000 | G16: 24000
... A49: 46357 | B49: Optimistic | C49: 6500 | D49: 17.5 | E49: 113750 | F49: 51000 | G49: 62750
A50: 46388 | B50: Pessimistic | C50: 3500 | D50: 12 | E50: 42000 | F50: 53550 | G50: -11550 | J50: =F50/F49 -> 1.05
A51: 46419 | B51: Pessimistic | C51: 3500 | D51: 12 | E51: 42000 | F51: 53550 | G51: -11550
A52: 46447 | B52: Pessimistic | C52: 3500 | D52: 12 | E52: 42000 | F52: 53550 | G52: -11550
A53: 46478 | B53: Pessimistic | C53: 3500 | D53: 12 | E53: 42000 | F53: 53550 | G53: -11550
A54: 46508 | B54: Pessimistic | C54: 3500 | D54: 12 | E54: 42000 | F54: 53550 | G54: -11550
A55: 46539 | B55: Pessimistic | C55: 3500 | D55: 12 | E55: 42000 | F55: 53550 | G55: -11550
A56: 46569 | B56: Pessimistic | C56: 3500 | D56: 12 | E56: 42000 | F56: 53550 | G56: -11550
A57: 46600 | B57: Pessimistic | C57: 3500 | D57: 12 | E57: 42000 | F57: 53550 | G57: -11550
A58: 46631 | B58: Pessimistic | C58: 3500 | D58: 12 | E58: 42000 | F58: 53550 | G58: -11550
A59: 46661 | B59: Pessimistic | C59: 3500 | D59: 12 | E59: 42000 | F59: 53550 | G59: -11550
A60: 46692 | B60: Pessimistic | C60: 3500 | D60: 12 | E60: 42000 | F60: 53550 | G60: -11550
A61: 46722 | B61: Pessimistic | C61: 3500 | D61: 12 | E61: 42000 | F61: 53550 | G61: -11550
A62: 46023 | B62: Pessimistic | C62: 3500 | D62: 12 | E62: 42000 | F62: 53550 | G62: -11550
... A73: 46357 | B73: Pessimistic | C73: 3500 | D73: 12 | E73: 42000 | F73: 53550 | G73: -11550
C76: Projected Customer | D76: 1
C77: Base | D77: 1 | I77: 1
C78: Optimistic | D78: 1.3 | I78: 1.3
C79: Pessimistic | D79: 0.7 | I79: 0.7
C82: Average Basket | D82: 1
C83: Base | D83: 1 | I83: 0.8
C84: Optimistic | D84: 1.1666667 | I84: 1.1666667
C85: Pessimistic | D85: 0.8 | I85: 1

Sheet Cost Assumptions
A1: Cost_Item | B1: Estimated_Cost_EUR | C1: Type
A2: Rent (monthly) | B2: 12000 | C2: OpEx
A3: Salaries (monthly) | B3: 30000 | C3: OpEx
A4: Marketing (monthly) | B4: 5000 | C4: OpEx
A5: Utilities (monthly) | B5: 4000 | C5: OpEx
A6: Initial Setup | B6: 250000 | C6: CapEx
A7: Logistics | B7: 15000 | C7: CapEx
A8: IT Infrastructure | B8: 20000 | C8: CapEx
A9: Legal & Licensing | B9: 10000 | C9: CapEx
A10: Inventory (initial) | B10: 50000 | C10: OpEx
A11: Contingency Fund | B11: 10000 | C11: CapEx
A13: Days per week | B13: 7
A14: Weeks per month | B14: 4
A15: Number of months | B15: 12
A16: Years | B16: 2
A19: OPEX | B19: 1
A20: Base | B20: 1 | K20: 1
A21: Optimistic | B21: 0.9 | K21: 0.9
A22: Pessimistic | B22: 1.05 | K22: 1.05

Sheet Workings
A1: Cost Scenario:
A2: Customer Scenario:
A3: Basket Scenario:
E4: EuroGro Retail Group
B5: Workings
E7: 2025 | F7: 2026 | G7: 2027
B8: Number of Months | C8: 12
B10: Capital Expenses
C12: Initial Setup | F12: ='Cost Assumptions'!B6 -> 250000 | G12: 0
C13: Logistics | F13: ='Cost Assumptions'!B7 -> 15000 | G13: 0
C14: IT Infrastructure | F14: ='Cost Assumptions'!B8 -> 20000 | G14: 0
C15: Legal & Licensing | F15: ='Cost Assumptions'!B9 -> 10000 | G15: 0
C16: Contingency Fund | F16: ='Cost Assumptions'!B11 -> 10000 | G16: 0
B17: Total Capex | F17: =SUM(F12:F16) -> 305000 | G17: =SUM(G12:G16) -> 0
B20: Operating Expenses
C22: Inventory | F22: {=INDEX('Cost Assumptions'!$B$20:$B$22,'Cost Assumptions'!$B$19)*('Cost Assumptions'!B10)} -> 50000 | G22: =F22 -> 50000
C23: Rent | F23: {=INDEX('Cost Assumptions'!$B$20:$B$22,'Cost Assumptions'!$B$19)*('Cost Assumptions'!B2*$C$8)} -> 144000 | G23: {=INDEX('Cost Assumptions'!$B$20:$B$22,'Cost Assumptions'!$B$19)*('Cost Assumptions'!B2*$C$8)} -> 144000
C24: Salaries | F24: {=INDEX('Cost Assumptions'!$B$20:$B$22,'Cost Assumptions'!$B$19)*('Cost Assumptions'!B3*$C$8)} -> 360000 | G24: {=INDEX('Cost Assumptions'!$B$20:$B$22,'Cost Assumptions'!$B$19)*('Cost Assumptions'!B3*$C$8)} -> 360000
C25: Marketing | F25: {=INDEX('Cost Assumptions'!$B$20:$B$22,'Cost Assumptions'!$B$19)*('Cost Assumptions'!B4*$C$8)} -> 60000 | G25: {=INDEX('Cost Assumptions'!$B$20:$B$22,'Cost Assumptions'!$B$19)*('Cost Assumptions'!B4*$C$8)} -> 60000
C26: Utilities | F26: {=INDEX('Cost Assumptions'!$B$20:$B$22,'Cost Assumptions'!$B$19)*('Cost Assumptions'!B5*$C$8)} -> 48000 | G26: {=INDEX('Cost Assumptions'!$B$20:$B$22,'Cost Assumptions'!$B$19)*('Cost Assumptions'!B5*$C$8)} -> 48000
B27: Total Opex | F27: =SUM(F22:F26) -> 662000 | G27: =SUM(G22:G26) -> 662000
B30: Revenue & Profit
B32: Projected Customer | F32: {=INDEX('Revenue Assumptions'!$D$77:$D$79,'Revenue Assumptions'!$D$76)*('Revenue Assumptions'!C2)} -> 5000 | G32: =F32 -> 5000
B34: Average Basket | F34: {=INDEX('Revenue Assumptions'!$D$83:$D$85,'Revenue Assumptions'!$D$82)*('Revenue Assumptions'!D2)} -> 15 | G34: =F34 -> 15
B36: Revenue | F36: =F32*F34*$C$8 -> 900000 | G36: =G32*G34*$C$8 -> 900000
B39: Net Profit | F39: =F36-F27 -> 238000 | G39: =G36-G27 -> 238000

Sheet Cost
A1: Cost Scenario:
A2: Customer Scenario:
A3: Basket Scenario:
E4: EuroGro Retail Group
B5: Cost Modelling
E7: 2025 | F7: 2026 | G7: 2027
B10: Total Cost
B12: Total Capex | E12: =Workings!E17 -> 0 | F12: =Workings!F17 -> 305000 | G12: =Workings!G17 -> 0
B14: Total Opex | E14: {=INDEX('Cost Assumptions'!$B$20:$B$22,'Cost Assumptions'!$B$19)*(Workings!E27)} -> 0 | F14: {=INDEX('Cost Assumptions'!$B$20:$B$22,'Cost Assumptions'!$B$19)*(Workings!F27)} -> 662000 | G14: {=INDEX('Cost Assumptions'!$B$20:$B$22,'Cost Assumptions'!$B$19)*(Workings!G27)} -> 662000
B16: Total Cost | E16: =SUM(E12:E14) -> 0 | F16: =SUM(F12:F14) -> 967000 | G16: =SUM(G12:G14) -> 662000
B18: Monthly opex | C18: =F14/Workings!C8 -> 55166.667

Sheet Revenue
A1: Cost Scenario:
A2: Customer Scenario:
A3: Basket Scenario:
E4: EuroGro Retail Group
B5: Revenue
E7: 2025 | F7: 2026 | G7: 2027
B10: Total Revenue
B12: Projected Customer | E12: {=INDEX('Revenue Assumptions'!$D$77:$D$79,'Revenue Assumptions'!$D$76)*(Workings!E32)} -> 0 | F12: {=INDEX('Revenue Assumptions'!$D$77:$D$79,'Revenue Assumptions'!$D$76)*(Workings!F32)} -> 5000 | G12: {=INDEX('Revenue Assumptions'!$D$77:$D$79,'Revenue Assumptions'!$D$76)*(Workings!G32)} -> 5000
B14: Average Basket | E14: {=INDEX('Revenue Assumptions'!$D$83:$D$85,'Revenue Assumptions'!$D$82)*(Workings!E34)} -> 0 | F14: {=INDEX('Revenue Assumptions'!$D$83:$D$85,'Revenue Assumptions'!$D$82)*Workings!F34} -> 15 | G14: {=INDEX('Revenue Assumptions'!$D$83:$D$85,'Revenue Assumptions'!$D$82)*Workings!G34} -> 15
B16: Revenue | E16: =E12*E14*Workings!$C$8 -> 0 | F16: =F12*F14*Workings!$C$8 -> 900000 | G16: =G12*G14*Workings!$C$8 -> 900000
B19: Net Profit | E19: =E16-Cost!E14 -> 0 | F19: =F16-Cost!F14 -> 238000 | G19: =G16-Cost!G14 -> 238000
B21: Monthly Net Profit | D21: =G19/'Cost Assumptions'!B15 -> 19833.333

Sheet Breakeven_ROI
A1: Cost Scenario:
A2: Customer Scenario:
A3: Basket Scenario:
E4: EuroGro Retail Group
B5: Breakeven & ROI
E7: 2025 | F7: 2026 | G7: 2027
B11: Total Opex | E11: =Cost!E14 -> 0 | F11: =Cost!F14 -> 662000 | G11: =Cost!G14 -> 662000
B13: Total Cost | E13: =Cost!E16 -> 0 | F13: =Cost!F16 -> 967000 | G13: =Cost!G16 -> 662000
B15: Total Revenue | E15: =Revenue!E16 -> 0 | F15: =Revenue!F16 -> 900000 | G15: =Revenue!G16 -> 900000
B17: Breakeven Time = (in Month) | C17: Total Cost
C18: Total Revenue - Total Opex | F18: =Cost!F12/Revenue!D21 -> 15.378151
B21: ROI = | C21: Total Revenue - Total Opex
C22: Total Cost (Capex+Opex) | F22: =(F15-F11)/F13 -> 0.24612203 | G22: =(G15-G11)/G13 -> 0.35951662

Sheet Summary
A1: Cost Scenario:
A2: Customer Scenario:
A3: Basket Scenario:
C4: EuroGro Retail Group
B5: Summary
B6: Parameters | C6: 2025 | D6: 2026 | E6: 2027
B7: Total Capex | C7: =Cost!E12 -> 0 | D7: =Cost!F12 -> 305000 | E7: =Cost!G12 -> 0
B8: Total Opex | C8: =Cost!E14 -> 0 | D8: =Cost!F14 -> 662000 | E8: =Cost!G14 -> 662000
B9: Total Cost | C9: =Cost!E16 -> 0 | D9: =Cost!F16 -> 967000 | E9: =Cost!G16 -> 662000
B10: Total Revenue | C10: =Revenue!E16 -> 0 | D10: =Revenue!F16 -> 900000 | E10: =Revenue!G16 -> 900000
B11: Net Profit | C11: =Revenue!E19 -> 0 | D11: =Revenue!F19 -> 238000 | E11: =Revenue!G19 -> 238000
B12: Return on Investment (ROI) | D12: =Breakeven_ROI!F22 -> 0.24612203 | E12: =Breakeven_ROI!G22 -> 0.35951662
B13: Breakeven Time | D13: =Breakeven_ROI!F18 -> 15.378151 | E13: =Summary[[#This Row],[2026]] -> 15.378151

Sheet Dataset
A1: Cost Scenario:
A2: Customer Scenario:
A3: Basket Scenario:
F4: EuroGro Retail Group
B5: Dataset
C6: Year | D6: Capex Items | E6: Capex | F6: Opex Items | G6: Opex | H6: Total Cost | I6: Total Revenue | J6: Net Profit | K6: Profit Margin | L6: ROI | M6: Breakeven Time
C7: 2026 | H7: =Cost!F16 -> 967000 | I7: =Revenue!F16 -> 900000 | J7: =Revenue!F19 -> 238000 | K7: =Data[[#This Row],[Net Profit]]/Data[[#This Row],[Total Revenue]] -> 0.26444444 | L7: =Breakeven_ROI!F22 -> 0.24612203 | M7: =Breakeven_ROI!F18 -> 15.378151
C8: 2027 | H8: =Cost!G16 -> 662000 | I8: =Revenue!G16 -> 900000 | J8: =Revenue!G19 -> 238000 | K8: =Data[[#This Row],[Net Profit]]/Data[[#This Row],[Total Revenue]] -> 0.26444444 | L8: =Breakeven_ROI!G22 -> 0.35951662 | M8: =Breakeven_ROI!F18 -> 15.378151
C9: 2026 | D9: =Workings!C12 -> Initial Setup | E9: =Workings!F12 -> 250000
C10: 2026 | D10: =Workings!C13 -> Logistics | E10: =Workings!F13 -> 15000 | F10: =Workings!C22 -> Inventory | G10: =Workings!F22 -> 50000
C11: 2026 | D11: =Workings!C14 -> IT Infrastructure | E11: =Workings!F14 -> 20000 | F11: =Workings!C23 -> Rent | G11: =Workings!F23 -> 144000
C12: 2026 | D12: =Workings!C15 -> Legal & Licensing | E12: =Workings!F15 -> 10000 | F12: =Workings!C24 -> Salaries | G12: =Workings!F24 -> 360000
C13: 2026 | D13: =Workings!C16 -> Contingency Fund | E13: =Workings!F16 -> 10000 | F13: =Workings!C25 -> Marketing | G13: =Workings!F25 -> 60000
C14: 2026 | F14: =Workings!C26 -> Utilities | G14: =Workings!F26 -> 48000
C15: 2027 | F15: =Workings!C22 -> Inventory | G15: =Workings!G22 -> 50000
C16: 2027 | F16: =Workings!C23 -> Rent | G16: =Workings!G23 -> 144000
C17: 2027 | F17: =Workings!C24 -> Salaries | G17: =Workings!G24 -> 360000
C18: 2027 | F18: =Workings!C25 -> Marketing | G18: =Workings!G25 -> 60000
C19: 2027 | F19: =Workings!C26 -> Utilities | G19: =Workings!G26 -> 48000

Sheet Pivot
A3: Sum of Capex | B3: Sum of Opex | C3: Sum of Total Cost | D3: Sum of Total Revenue | E3: Sum of Net Profit | F3: Avg. ROI | G3: Breakeven | H3: Net Profit Margin
A4: 305000 | B4: 1324000 | C4: 1629000 | D4: 1800000 | E4: 476000 | F4: 0.30281932 | G4: 15.378151 | H4: 0.26444444
A7: Capex Items | B7: Sum of Capex | D7: Year | E7: Op. Exp | F7: Revenue | G7: Profit
A8: Contingency Fund | B8: 10000 | D8: 2026 | E8: 662000 | F8: 900000 | G8: 238000
A9: Legal & Licensing | B9: 10000 | D9: 2027 | E9: 662000 | F9: 900000 | G9: 238000
A10: Logistics | B10: 15000 | D10: Grand Total | E10: 1324000 | F10: 1800000 | G10: 476000
A11: IT Infrastructure | B11: 20000
A12: Initial Setup | B12: 250000
A13: Total Capex | B13: 305000
D14: Year | E14: Profit Margin % | F14: ROI %
D15: 2026 | E15: 0.26444444 | F15: 0.24612203
D16: 2027 | E16: 0.26444444 | F16: 0.35951662
A17: Opex Items | B17: Sum of Opex | D17: Grand Total | E17: 0.52888889 | F17: 0.60563864
A18: Marketing | B18: 120000
A19: Rent | B19: 288000
A20: Salaries | B20: 720000
A21: Utilities | B21: 96000
A22: Inventory | B22: 100000
A23: Grand Total | B23: 1324000

Sheet Dashboard
R3: Cost Scenario
R4: Customer Scenario
R5: Basket Scenario
